demo/__init__.py
demo/fakechat_langchain.py
demo/mockgpt_langchain.py
demo/mockgpt_runnable_langchain.py
demo/openai_langchain.py
demo/fastapi_langchain/__init__.py
demo/fastapi_langchain/main.py
vishwa/__init__.py
vishwa/client/__init__.py
vishwa/client/constants.py
vishwa/client/models.py
vishwa/client/xpuls_client.py
vishwa/mlmonitor/__init__.py
vishwa/mlmonitor/langchain/__init__.py
vishwa/mlmonitor/langchain/instrument.py
vishwa/mlmonitor/langchain/xpuls_client.py
vishwa/mlmonitor/langchain/decorators/__init__.py
vishwa/mlmonitor/langchain/decorators/map_xpuls_project.py
vishwa/mlmonitor/langchain/decorators/telemetry_override_labels.py
vishwa/mlmonitor/langchain/handlers/__init__.py
vishwa/mlmonitor/langchain/handlers/callback_handlers.py
vishwa/mlmonitor/langchain/handlers/constants.py
vishwa/mlmonitor/langchain/patches/__init__.py
vishwa/mlmonitor/langchain/patches/patch_invoke.py
vishwa/mlmonitor/langchain/patches/patch_run.py
vishwa/mlmonitor/langchain/patches/utils.py
vishwa/mlmonitor/langchain/patches/xp_prompt_template.py
vishwa/mlmonitor/langchain/profiling/__init__.py
vishwa/mlmonitor/langchain/profiling/prometheus.py
vishwa/mlmonitor/utils/__init__.py
vishwa/mlmonitor/utils/common.py
vishwa/prompt_hub/__init__.py
vishwa/prompt_hub/prompt.py
vishwa_ml_sdk-0.4.0.dist-info/LICENSE
vishwa_ml_sdk-0.4.0.dist-info/METADATA
vishwa_ml_sdk-0.4.0.dist-info/WHEEL
vishwa_ml_sdk-0.4.0.dist-info/top_level.txt
vishwa_ml_sdk-0.4.0.dist-info/RECORD
