Metadata-Version: 2.1
Name: vishwa-ml-sdk
Version: 0.4.0
Summary: Integration SDK for vishwa.ai
Home-page: https://github.com/vishwa-labs/vishwa-ml-sdk
Author: Sai Sharan Tangeda
Author-email: saisarantangeda@gmail.com
License: Apache License 2.0
License-File: LICENSE
Requires-Dist: prometheus-client
Requires-Dist: pydantic
Requires-Dist: requests
Requires-Dist: urllib3
Requires-Dist: langchain
Provides-Extra: all
Requires-Dist: prometheus-client ; extra == 'all'
Requires-Dist: pydantic ; extra == 'all'
Requires-Dist: requests ; extra == 'all'
Requires-Dist: urllib3 ; extra == 'all'
Requires-Dist: langchain ; extra == 'all'
Provides-Extra: langchain
Requires-Dist: prometheus-client ; extra == 'langchain'
Requires-Dist: pydantic ; extra == 'langchain'
Requires-Dist: requests ; extra == 'langchain'
Requires-Dist: urllib3 ; extra == 'langchain'
Requires-Dist: langchain ; extra == 'langchain'
